gists.py
vebai_gists.py
vebai_gists1.py
vebai_gists1-0.0.1.dist-info/METADATA
vebai_gists1-0.0.1.dist-info/WHEEL
vebai_gists1-0.0.1.dist-info/top_level.txt
vebai_gists1-0.0.1.dist-info/RECORD
