Metadata-Version: 2.1
Name: vebai-gists1
Version: 0.0.1
Summary: Get gists and notify when new gists are published
Home-page: UNKNOWN
Author: Victor Ebai
Author-email: UNKNOWN
License: UNKNOWN
Platform: UNKNOWN
